LICENSE
MANIFEST.in
README.md
setup.py
wasienv/__init__.py
wasienv/commands.py
wasienv/constants.py
wasienv/sdk.py
wasienv/tools.py
wasienv/wasiar.py
wasienv/wasicc.py
wasienv/wasiconfigure.py
wasienv/wasienv.cmake
wasienv/wasienv.py
wasienv/wasild.py
wasienv/wasimake.py
wasienv/wasinm.py
wasienv/wasiranlib.py
wasienv/wasirun.py
wasienv/wasiswiftc.py
wasienv/wasmcc.py
wasienv.egg-info/PKG-INFO
wasienv.egg-info/SOURCES.txt
wasienv.egg-info/dependency_links.txt
wasienv.egg-info/entry_points.txt
wasienv.egg-info/not-zip-safe
wasienv.egg-info/requires.txt
wasienv.egg-info/top_level.txt
wasienv/stubs/.gitignore
wasienv/stubs/dirent.h
wasienv/stubs/dlfcn.h
wasienv/stubs/err.h
wasienv/stubs/grp.h
wasienv/stubs/netdb.h
wasienv/stubs/preamble.h
wasienv/stubs/pthread.h
wasienv/stubs/pty.h
wasienv/stubs/pwd.h
wasienv/stubs/termios.h
wasienv/stubs/bits/ioctl.h
wasienv/stubs/bits/termios.h
wasienv/stubs/net/if.h
wasienv/stubs/netinet/in.h
wasienv/stubs/sys/ioctl.h
wasienv/stubs/sys/statvfs.h
wasienv/stubs/sys/wait.h
wasienv/stubs/sys/xattr.h