Metadata-Version: 2.1
Name: wasienv
Version: 0.5.4
Summary: wasienv is a toolchain for WASI
Home-page: https://github.com/wasienv-core/wasienv
Author: Syrus Akbary
Author-email: syrus@wasmer.io
License: MIT
Keywords: webassembly wasi wasienv wasmer
Platform: UNKNOWN
